inmanta_plugins/podman/__init__.py
inmanta_plugins/podman/setup.cfg
inmanta_plugins/podman/files/.gitkeep
inmanta_plugins/podman/model/_init.cf
inmanta_plugins/podman/model/container.cf
inmanta_plugins/podman/model/container_like.cf
inmanta_plugins/podman/model/helpers.cf
inmanta_plugins/podman/model/network.cf
inmanta_plugins/podman/model/services/_init.cf
inmanta_plugins/podman/model/services/systemd_auto_update.cf
inmanta_plugins/podman/model/services/systemd_container.cf
inmanta_plugins/podman/model/services/systemd_pod.cf
inmanta_plugins/podman/model/services/systemd_service.cf
inmanta_plugins/podman/resources/__init__.py
inmanta_plugins/podman/resources/abc.py
inmanta_plugins/podman/resources/image.py
inmanta_plugins/podman/resources/image_discovery.py
inmanta_plugins/podman/resources/network.py
inmanta_plugins/podman/resources/network_discovery.py
inmanta_plugins/podman/templates/.gitkeep
inmanta_plugins/podman/templates/service.container.j2
inmanta_module_podman-1.9.0.dist-info/METADATA
inmanta_module_podman-1.9.0.dist-info/WHEEL
inmanta_module_podman-1.9.0.dist-info/top_level.txt
inmanta_module_podman-1.9.0.dist-info/RECORD
