Metadata-Version: 2.4
Name: inmanta-module-podman
Version: 1.9.0
Summary: Simple module to manage podman resources
Author: Guillaume Everarts de Velp
Author-email: edvgui@gmail.com
License: ASL 2.0
Requires-Dist: inmanta-module-std<9,>=4.0
Requires-Dist: inmanta-module-exec<3,>=2.0.0
Requires-Dist: inmanta-module-files<3,>=2.5.0
Requires-Dist: inmanta-module-mitogen<1,>=0.1.0
Requires-Dist: inmanta-core>=15.1.0
